{
  "version": 2,
  "templates": [
    {
      "id": "in-crm-hubspot",
      "name": "IN-CRM-HUBSPOT",
      "description": "Full workflow to ...",
      "path": "in-crm-hubspot",
      "versions": [
        {
          "version": "0.0.1",
          "description": "",
          "stable": false,
          "path": "v0"
        }
      ]
    },
    {
      "id": "in-crm-salesforce",
      "name": "IN-CRM-SALESFORCE",
      "description": "Full workflow to ...",
      "path": "in-crm-salesforce",
      "versions": [
        {
          "version": "0.0.1",
          "description": "",
          "stable": false,
          "path": "v0"
        }
      ]
    },
    {
      "id": "out-crm-snowflake",
      "name": "OUT-CRM-SNOWFLAKE",
      "description": "Full workflow to ...",
      "path": "out-crm-snowflake",
      "versions": [
        {
          "version": "0.0.1",
          "description": "",
          "stable": false,
          "path": "v0"
        }
      ]
    }
  ]
}
